{
  "Blocks": [
    {
      "BlockType": "KEY_VALUE_SET",
      "Confidence": 90.77305603027344,
      "Geometry": {
        "BoundingBox": {
          "Width": 0.07167059928178787,
          "Height": 0.01282162219285965,
          "Left": 0.058137983083724976,
          "Top": 0.8508346676826477
        },
        "Polygon": [
          {
            "X": 0.058138035237789154,
            "Y": 0.8508347272872925
          },
          {
            "X": 0.12980858981609344,
            "Y": 0.8508346676826477
          },
          {
            "X": 0.12980853021144867,
            "Y": 0.8636561632156372
          },
          {
            "X": 0.058137983083724976,
            "Y": 0.8636562824249268
          }
        ]
      },
      "Id": "07f93515-8bc2-44f7-b177-1844838514c6",
      "Relationships": [
        {
          "Type": "VALUE",
          "Ids": [
            "ca30277e-efd4-4241-86ad-813282e14606"
          ]
        },
        {
          "Type": "CHILD",
          "Ids": [
            "9c6824c3-c858-4392-9e4f-fb36051febba"
          ]
        }
      ],
      "EntityTypes": [
        "KEY"
      ],
      "Page": 1
    },
    {
      "BlockType": "KEY_VALUE_SET",
      "Confidence": 84.12920379638672,
      "Geometry": {
        "BoundingBox": {
          "Width": 0.07146190851926804,
          "Height": 0.012776748277246952,
          "Left": 0.05819055810570717,
          "Top": 0.7502912282943726
        },
        "Polygon": [
          {
            "X": 0.05819060653448105,
            "Y": 0.7502912878990173
          },
          {
            "X": 0.1296524703502655,
            "Y": 0.7502912282943726
          },
          {
            "X": 0.12965241074562073,
            "Y": 0.763067901134491
          },
          {
            "X": 0.05819055810570717,
            "Y": 0.7630679607391357
          }
        ]
      },
      "Id": "3b2cb497-c67b-40c8-8674-d0d9f547da99",
      "Relationships": [
        {
          "Type": "VALUE",
          "Ids": [
            "7b5d4b09-6cdd-430f-8b40-b5e93aa64589"
          ]
        },
        {
          "Type": "CHILD",
          "Ids": [
            "3d0277f9-9069-4b2d-aa82-16bb2748008b"
          ]
        }
      ],
      "EntityTypes": [
        "KEY"
      ],
      "Page": 1
    },
    {
      "BlockType": "KEY_VALUE_SET",
      "Confidence": 84.12920379638672,
      "Geometry": {
        "BoundingBox": {
          "Width": 0.3746201992034912,
          "Height": 0.022511335089802742,
          "Left": 0.05825036019086838,
          "Top": 0.7219808101654053
        },
        "Polygon": [
          {
            "X": 0.05825044587254524,
            "Y": 0.7219810485839844
          },
          {
            "X": 0.4328705668449402,
            "Y": 0.7219808101654053
          },
          {
            "X": 0.43287041783332825,
            "Y": 0.7444918155670166
          },
          {
            "X": 0.05825036019086838,
            "Y": 0.7444921135902405
          }
        ]
      },
      "Id": "7b5d4b09-6cdd-430f-8b40-b5e93aa64589",
      "EntityTypes": [
        "VALUE"
      ],
      "Page": 1
    },
    {
      "BlockType": "KEY_VALUE_SET",
      "Confidence": 90.77305603027344,
      "Geometry": {
        "BoundingBox": {
          "Width": 0.39123106002807617,
          "Height": 0.02288038097321987,
          "Left": 0.05841871351003647,
          "Top": 0.822428286075592
        },
        "Polygon": [
          {
            "X": 0.05841880291700363,
            "Y": 0.822428822517395
          },
          {
            "X": 0.44964978098869324,
            "Y": 0.822428286075592
          },
          {
            "X": 0.4496496319770813,
            "Y": 0.8453080654144287
          },
          {
            "X": 0.05841871351003647,
            "Y": 0.8453086614608765
          }
        ]
      },
      "Id": "ca30277e-efd4-4241-86ad-813282e14606",
      "EntityTypes": [
        "VALUE"
      ],
      "Page": 1
    }
  ]
}