{
  "Blocks": [
    {
      "BlockType": "KEY_VALUE_SET",
      "Confidence": 92.21431732177734,
      "Geometry": {
        "BoundingBox": {
          "Width": 0.28307613730430603,
          "Height": 0.015576652251183987,
          "Left": 0.1174028217792511,
          "Top": 0.0925913006067276
        },
        "Polygon": [
          {
            "X": 0.11740284413099289,
            "Y": 0.0925913006067276
          },
          {
            "X": 0.40047895908355713,
            "Y": 0.09259261190891266
          },
          {
            "X": 0.40047892928123474,
            "Y": 0.10816795378923416
          },
          {
            "X": 0.1174028217792511,
            "Y": 0.10816668719053268
          }
        ]
      },
      "Id": "68a16d17-6314-49e4-b2f2-0c33d77101fe",
      "Relationships": [
        {
          "Type": "VALUE",
          "Ids": [
            "bd176888-e8c4-41c9-aaa9-9613ab2942c5"
          ]
        },
        {
          "Type": "CHILD",
          "Ids": [
            "a2bf4acc-66cc-4726-993b-be0545224664",
            "75a49064-0287-4169-8de4-df1fe11f48d1"
          ]
        }
      ],
      "EntityTypes": [
        "KEY"
      ],
      "Page": 3
    },
    {
      "BlockType": "KEY_VALUE_SET",
      "Confidence": 93.29153442382812,
      "Geometry": {
        "BoundingBox": {
          "Width": 0.165771484375,
          "Height": 0.015520402230322361,
          "Left": 0.11734236776828766,
          "Top": 0.19719445705413818
        },
        "Polygon": [
          {
            "X": 0.11734236776828766,
            "Y": 0.19719605147838593
          },
          {
            "X": 0.28311386704444885,
            "Y": 0.19719445705413818
          },
          {
            "X": 0.28311383724212646,
            "Y": 0.21271327137947083
          },
          {
            "X": 0.11734239012002945,
            "Y": 0.21271485090255737
          }
        ]
      },
      "Id": "49ce3372-03bc-4b06-96bb-e7629a811fba",
      "Relationships": [
        {
          "Type": "VALUE",
          "Ids": [
            "3b8f8d1d-94b6-42c0-8f6c-6a5466112472"
          ]
        },
        {
          "Type": "CHILD",
          "Ids": [
            "f75e65d5-c86d-47e2-9f9f-eb636358e15b",
            "a2170b27-0da6-4c0d-afcb-b8ead5e478e6"
          ]
        }
      ],
      "EntityTypes": [
        "KEY"
      ],
      "Page": 5
    },
    {
      "BlockType": "KEY_VALUE_SET",
      "Confidence": 92.21431732177734,
      "Geometry": {
        "BoundingBox": {
          "Width": 0.2640577554702759,
          "Height": 0.018509695306420326,
          "Left": 0.40542230010032654,
          "Top": 0.08928915113210678
        },
        "Polygon": [
          {
            "X": 0.4054223299026489,
            "Y": 0.08928915113210678
          },
          {
            "X": 0.6694800853729248,
            "Y": 0.08929038047790527
          },
          {
            "X": 0.66948002576828,
            "Y": 0.10779884457588196
          },
          {
            "X": 0.40542230010032654,
            "Y": 0.10779765993356705
          }
        ]
      },
      "Id": "bd176888-e8c4-41c9-aaa9-9613ab2942c5",
      "EntityTypes": [
        "VALUE"
      ],
      "Page": 3
    },
    {
      "BlockType": "KEY_VALUE_SET",
      "Confidence": 93.29153442382812,
      "Geometry": {
        "BoundingBox": {
          "Width": 0.3841853141784668,
          "Height": 0.022041188552975655,
          "Left": 0.28865906596183777,
          "Top": 0.18988554179668427
        },
        "Polygon": [
          {
            "X": 0.28865906596183777,
            "Y": 0.18988925218582153
          },
          {
            "X": 0.672844409942627,
            "Y": 0.18988554179668427
          },
          {
            "X": 0.6728442907333374,
            "Y": 0.2119230479001999
          },
          {
            "X": 0.28865906596183777,
            "Y": 0.21192672848701477
          }
        ]
      },
      "Id": "3b8f8d1d-94b6-42c0-8f6c-6a5466112472",
      "EntityTypes": [
        "VALUE"
      ],
      "Page": 5
    }
  ]
}